CHANGES.txt
CONTRIBUTORS.txt
MANIFEST.in
README.txt
setup.cfg
setup.py
docs/HISTORY.txt
docs/INSTALL.txt
docs/LICENSE.GPL
docs/LICENSE.txt
vs/__init__.py
vs.tdi.egg-info/PKG-INFO
vs.tdi.egg-info/SOURCES.txt
vs.tdi.egg-info/dependency_links.txt
vs.tdi.egg-info/entry_points.txt
vs.tdi.egg-info/namespace_packages.txt
vs.tdi.egg-info/not-zip-safe
vs.tdi.egg-info/paster_plugins.txt
vs.tdi.egg-info/requires.txt
vs.tdi.egg-info/top_level.txt
vs/tdi/README.txt
vs/tdi/__init__.py
vs/tdi/config.py
vs/tdi/configure.zcml
vs/tdi/header.txt
vs/tdi/browser/__init__.py
vs/tdi/browser/configure.zcml
vs/tdi/browser/folder.py
vs/tdi/browser/tdi_ajax_view.pt
vs/tdi/browser/tdi_view.pt
vs/tdi/browser/resources/tabs.css
vs/tdi/browser/resources/tabs.png
vs/tdi/content/__init__.py
vs/tdi/content/configure.zcml
vs/tdi/extenders/__init__.py
vs/tdi/extenders/all.py
vs/tdi/extenders/configure.zcml
vs/tdi/interfaces/__init__.py
vs/tdi/locales/de/LC_MESSAGES/atcontenttypes.mo
vs/tdi/locales/de/LC_MESSAGES/atcontenttypes.po
vs/tdi/locales/de/LC_MESSAGES/plone.mo
vs/tdi/locales/de/LC_MESSAGES/plone.po
vs/tdi/portlets/__init__.py
vs/tdi/portlets/configure.zcml
vs/tdi/profiles/default/cssregistry.xml
vs/tdi/profiles/default/metadata.xml
vs/tdi/profiles/default/portlets.xml
vs/tdi/profiles/default/propertiestool.xml
vs/tdi/profiles/default/types/Folder.xml
vs/tdi/tests/__init__.py
vs/tdi/tests/base.py
vs/tdi/tests/test_doctest.py