Metadata-Version: 1.0
Name: vs.tdi
Version: 0.3.2
Summary: vs.tdi (tabbed document interface)
Home-page: http://pypi.python.org/pypi/vs.tdi
Author: Andreas Jung
Author-email: info@zopyx.com
License: GPL
Keywords: Plone
Platform: UNKNOWN
Classifier: Framework :: Plone
Classifier: Framework :: Plone :: 4.0
Classifier: Framework :: Plone :: 4.1
Classifier: Framework :: Plone :: 4.2
Classifier: Intended Audience :: Developers
Classifier: License :: OSI Approved :: GNU General Public License (GPL)
